usersconfig/TODO
usersconfig/__init__.py
usersconfig/configuration.py
usersconfig/default_config.yml
usersconfig-0.1.9.dist-info/METADATA
usersconfig-0.1.9.dist-info/WHEEL
usersconfig-0.1.9.dist-info/top_level.txt
usersconfig-0.1.9.dist-info/RECORD
