Metadata-Version: 2.1
Name: usersconfig
Version: 0.1.9
Summary: Library for application configuration management
Home-page: https://gitlab.com/alensiljak/usersconfig
Author: Alen Šiljak
License: GPL3
Project-URL: Source Code, https://gitlab.com/alensiljak/usersconfig.git
Keywords: configuration library yaml
Platform: UNKNOWN
Requires-Dist: pyxdg
Requires-Dist: pyyaml
